grn_stability_selection/__init__.py
grn_stability_selection/stability.py
grn_stability_selection-0.0.1.dist-info/LICENSE
grn_stability_selection-0.0.1.dist-info/METADATA
grn_stability_selection-0.0.1.dist-info/WHEEL
grn_stability_selection-0.0.1.dist-info/top_level.txt
grn_stability_selection-0.0.1.dist-info/RECORD
